fustor_registry_client/__init__.py
fustor_registry_client/client.py
fustor_registry_client/models.py
fustor_registry_client-0.2.16.dist-info/METADATA
fustor_registry_client-0.2.16.dist-info/WHEEL
fustor_registry_client-0.2.16.dist-info/top_level.txt
fustor_registry_client-0.2.16.dist-info/RECORD
