Metadata-Version: 2.4
Name: fustor-registry-client
Version: 0.2.16
Summary: Client for Fustor Registry service
License-Expression: MIT
Requires-Python: >=3.11
Requires-Dist: httpx>=0.27.0
Requires-Dist: pydantic>=2.11.7
Requires-Dist: fustor-common
